pymlbenchmark/__init__.py
pymlbenchmark/benchmark/__init__.py
pymlbenchmark/benchmark/bench_helper.py
pymlbenchmark/benchmark/benchmark_perf.py
pymlbenchmark/benchmark/profiler_class.py
pymlbenchmark/benchmark/sklearn_helper.py
pymlbenchmark/context/__init__.py
pymlbenchmark/context/machine.py
pymlbenchmark/datasets/__init__.py
pymlbenchmark/datasets/artificial.py
pymlbenchmark/datasets/real_data.py
pymlbenchmark/datasets/data/__init__.py
pymlbenchmark/datasets/data/onnxruntime_LogisticRegression.csv
pymlbenchmark/external/__init__.py
pymlbenchmark/external/onnxruntime_perf.py
pymlbenchmark/external/onnxruntime_perf_binclass.py
pymlbenchmark/external/onnxruntime_perf_list.py
pymlbenchmark/external/onnxruntime_perf_regression.py
pymlbenchmark/plotting/__init__.py
pymlbenchmark/plotting/plot_bench_results.py
pymlbenchmark/plotting/plot_bench_xtime.py
pymlbenchmark/plotting/plot_helper.py
pymlbenchmark-0.3.187.dist-info/LICENSE.txt
pymlbenchmark-0.3.187.dist-info/METADATA
pymlbenchmark-0.3.187.dist-info/WHEEL
pymlbenchmark-0.3.187.dist-info/top_level.txt
pymlbenchmark-0.3.187.dist-info/RECORD
