Metadata-Version: 2.1
Name: pymlbenchmark
Version: 0.3.187
Summary: Benchmarks about Machine Learning in Python.
Home-page: http://www.xavierdupre.fr/app/pymlbenchmark/helpsphinx/index.html
Author: Xavier Dupré
Author-email: xavier.dupre@gmail.com
License: MIT
Download-URL: https://github.com/sdpython/pymlbenchmark/
Keywords: pymlbenchmark,Xavier Dupré
Platform: UNKNOWN
Classifier: Programming Language :: Python :: 3
Classifier: Intended Audience :: Developers
Classifier: Topic :: Scientific/Engineering
Classifier: Topic :: Education
Classifier: License :: OSI Approved :: MIT License
Classifier: Development Status :: 5 - Production/Stable
Requires-Dist: pyquickhelper (>=1.10)
Requires-Dist: mlinsights (>=0.3)
Requires-Dist: pyinstrument
Requires-Dist: mlprodict (>=0.5)
